{"startDate":"2024-01-01","endDate":"2024-11-10","timeUnit":"week","results":[{"title":"두바이 여행","keywords":["아랍에미레이트","아랍에미레이트 여행","두바이","여행","해외여행"],"data":[{"period":"2024-01-01","ratio":47.34867},{"period":"2024-01-08","ratio":47.45612},{"period":"2024-01-15","ratio":53.67878},{"period":"2024-01-22","ratio":49.68718},{"period":"2024-01-29","ratio":58.17395},{"period":"2024-02-05","ratio":43.46897},{"period":"2024-02-12","ratio":40.59575},{"period":"2024-02-19","ratio":39.47736},{"period":"2024-02-26","ratio":40.62945},{"period":"2024-03-04","ratio":37.20244},{"period":"2024-03-11","ratio":42.15094},{"period":"2024-03-18","ratio":36.05226},{"period":"2024-03-25","ratio":34.81815},{"period":"2024-04-01","ratio":32.4504},{"period":"2024-04-08","ratio":34.49643},{"period":"2024-04-15","ratio":100},{"period":"2024-04-22","ratio":43.26678},{"period":"2024-04-29","ratio":36.99516},{"period":"2024-05-06","ratio":37.5623},{"period":"2024-05-13","ratio":37.04793},{"period":"2024-05-20","ratio":39.95803},{"period":"2024-05-27","ratio":51.31421},{"period":"2024-06-03","ratio":43.90259},{"period":"2024-06-10","ratio":41.95066},{"period":"2024-06-17","ratio":40.37957},{"period":"2024-06-24","ratio":41.09867},{"period":"2024-07-01","ratio":44.11241},{"period":"2024-07-08","ratio":48.36024},{"period":"2024-07-15","ratio":46.45663},{"period":"2024-07-22","ratio":45.9251},{"period":"2024-07-29","ratio":43.49186},{"period":"2024-08-05","ratio":42.89165},{"period":"2024-08-12","ratio":42.9635},{"period":"2024-08-19","ratio":41.06307},{"period":"2024-08-26","ratio":38.5974},{"period":"2024-09-02","ratio":39.16136},{"period":"2024-09-09","ratio":40.31917},{"period":"2024-09-16","ratio":38.09193},{"period":"2024-09-23","ratio":37.6049},{"period":"2024-09-30","ratio":37.87576},{"period":"2024-10-07","ratio":38.06841},{"period":"2024-10-14","ratio":36.30086},{"period":"2024-10-21","ratio":34.11686},{"period":"2024-10-28","ratio":32.3207},{"period":"2024-11-04","ratio":31.70206}]}]}