{"startDate":"2024-01-01","endDate":"2024-11-10","timeUnit":"week","results":[{"title":"캔버라 여행","keywords":["오스트레일리아","오스트레일리아 여행","캔버라","여행","해외여행"],"data":[{"period":"2024-01-01","ratio":80.94562},{"period":"2024-01-08","ratio":79.67266},{"period":"2024-01-15","ratio":79.77129},{"period":"2024-01-22","ratio":76.08956},{"period":"2024-01-29","ratio":97.94569},{"period":"2024-02-05","ratio":69.63228},{"period":"2024-02-12","ratio":73.63765},{"period":"2024-02-19","ratio":71.81605},{"period":"2024-02-26","ratio":68.11737},{"period":"2024-03-04","ratio":67.03396},{"period":"2024-03-11","ratio":70.93453},{"period":"2024-03-18","ratio":71.37683},{"period":"2024-03-25","ratio":68.29922},{"period":"2024-04-01","ratio":63.53871},{"period":"2024-04-08","ratio":64.0781},{"period":"2024-04-15","ratio":66.31888},{"period":"2024-04-22","ratio":65.48822},{"period":"2024-04-29","ratio":65.70706},{"period":"2024-05-06","ratio":65.45123},{"period":"2024-05-13","ratio":66.02145},{"period":"2024-05-20","ratio":68.30846},{"period":"2024-05-27","ratio":69.96671},{"period":"2024-06-03","ratio":70.24411},{"period":"2024-06-10","ratio":71.82375},{"period":"2024-06-17","ratio":73.40648},{"period":"2024-06-24","ratio":72.57274},{"period":"2024-07-01","ratio":71.79601},{"period":"2024-07-08","ratio":68.92337},{"period":"2024-07-15","ratio":68.77234},{"period":"2024-07-22","ratio":73.56213},{"period":"2024-07-29","ratio":83.52391},{"period":"2024-08-05","ratio":100},{"period":"2024-08-12","ratio":72.07341},{"period":"2024-08-19","ratio":65.22315},{"period":"2024-08-26","ratio":63.96097},{"period":"2024-09-02","ratio":61.41813},{"period":"2024-09-09","ratio":62.31352},{"period":"2024-09-16","ratio":61.62618},{"period":"2024-09-23","ratio":60.22068},{"period":"2024-09-30","ratio":56.56207},{"period":"2024-10-07","ratio":56.39717},{"period":"2024-10-14","ratio":57.28794},{"period":"2024-10-21","ratio":55.03945},{"period":"2024-10-28","ratio":54.48773},{"period":"2024-11-04","ratio":55.69442}]}]}